{"metadata":{},"options":{"compact":false,"sourceMaps":true,"ast":true,"babelrc":false,"configFile":false,"parserOpts":{"sourceType":"module","sourceFileName":"/Users/macbook/Desktop/Fedi/meteor/elearning/imports/ui/pages/new/new_post.jsx","plugins":["*","flow","jsx","asyncGenerators","bigInt","classPrivateMethods","classPrivateProperties","classProperties","doExpressions","dynamicImport","exportDefaultFrom","exportExtensions","exportNamespaceFrom","functionBind","functionSent","importMeta","nullishCoalescingOperator","numericSeparator","objectRestSpread","optionalCatchBinding","optionalChaining",["pipelineOperator",{"proposal":"minimal"}],"throwExpressions","dynamicImport","classProperties","classPrivateProperties","jsx",["flow",{}],"asyncGenerators","objectRestSpread","objectRestSpread",["flow",{}],"asyncGenerators"],"allowImportExportEverywhere":true,"allowReturnOutsideFunction":true,"strictMode":false},"caller":{"name":"meteor","arch":"web.browser"},"sourceFileName":"imports/ui/pages/new/new_post.jsx","filename":"/Users/macbook/Desktop/Fedi/meteor/elearning/imports/ui/pages/new/new_post.jsx","passPerPreset":false,"envName":"development","cwd":"/Users/macbook/Desktop/Fedi/meteor/elearning","root":"/Users/macbook/Desktop/Fedi/meteor/elearning","plugins":[{"key":"base$0$0","visitor":{"Program":{"enter":[null]},"_exploded":true,"_verified":true},"options":{"generateLetDeclarations":true,"enforceStrictMode":false}},{"key":"transform-meteor-dynamic-import","visitor":{"_exploded":{},"_verified":{},"CallExpression":{"enter":[null]}},"options":{}},{"key":"transform-runtime","visitor":{"CallExpression":{"enter":[null]},"BinaryExpression":{"enter":[null]},"MemberExpression":{"enter":[null],"exit":[null]},"_exploded":true,"_verified":true,"Identifier":{"enter":[null]},"JSXIdentifier":{"enter":[null]}},"options":{}},{"key":"proposal-class-properties","visitor":{"PrivateName":{"enter":[null]},"_exploded":true,"_verified":true,"ClassDeclaration":{"enter":[null]},"ClassExpression":{"enter":[null]}},"options":{"loose":true}},{"key":"transform-modules-commonjs","visitor":{"Program":{"exit":[null]},"_exploded":true,"_verified":true},"options":{"allowTopLevelThis":true,"strictMode":false,"loose":true}},{"key":"transform-react-jsx","visitor":{"_exploded":{},"_verified":{},"JSXNamespacedName":{"enter":[null]},"JSXElement":{"exit":[null]},"JSXFragment":{"exit":[null]},"Program":{"enter":[null],"exit":[null]},"JSXAttribute":{"enter":[null]}},"options":{"pragma":"React.createElement","pragmaFrag":"React.Fragment","throwIfNamespace":true,"useBuiltIns":false}},{"key":"transform-react-display-name","visitor":{"ExportDefaultDeclaration":{"enter":[null]},"CallExpression":{"enter":[null]},"_exploded":true,"_verified":true},"options":{}},{"key":"syntax-flow","visitor":{"_exploded":true,"_verified":true},"options":{}},{"key":"syntax-async-generators","visitor":{"_exploded":true,"_verified":true},"options":{}},{"key":"syntax-object-rest-spread","visitor":{"_exploded":true,"_verified":true},"options":{}},{"key":"transform-for-of","visitor":{"ForOfStatement":{"enter":[null]},"_exploded":true,"_verified":true},"options":{"loose":true}},{"key":"transform-literals","visitor":{"NumericLiteral":{"enter":[null]},"StringLiteral":{"enter":[null]},"_exploded":true,"_verified":true},"options":{}},{"key":"transform-template-literals","visitor":{"TaggedTemplateExpression":{"enter":[null]},"TemplateLiteral":{"enter":[null]},"_exploded":true,"_verified":true},"options":{}},{"key":"transform-parameters","visitor":{"_exploded":true,"_verified":true,"FunctionDeclaration":{"enter":[null]},"FunctionExpression":{"enter":[null]},"ObjectMethod":{"enter":[null]},"ArrowFunctionExpression":{"enter":[null]},"ClassMethod":{"enter":[null]},"ClassPrivateMethod":{"enter":[null]}},"options":{}},{"key":"proposal-object-rest-spread","visitor":{"_exploded":{},"_verified":{},"VariableDeclarator":{"enter":[null]},"ExportNamedDeclaration":{"enter":[null]},"CatchClause":{"enter":[null]},"AssignmentExpression":{"enter":[null]},"ObjectExpression":{"enter":[null]},"FunctionDeclaration":{"enter":[null]},"FunctionExpression":{"enter":[null]},"ObjectMethod":{"enter":[null]},"ArrowFunctionExpression":{"enter":[null]},"ClassMethod":{"enter":[null]},"ClassPrivateMethod":{"enter":[null]},"ForInStatement":{"enter":[null]},"ForOfStatement":{"enter":[null]}},"options":{}},{"key":"transform-flow-strip-types","visitor":{"_exploded":{},"_verified":{},"Program":{"enter":[null]},"ImportDeclaration":{"enter":[null,null]},"ClassProperty":{"enter":[null]},"ClassPrivateProperty":{"enter":[null]},"AssignmentPattern":{"enter":[null]},"TypeCastExpression":{"enter":[null,null]},"CallExpression":{"enter":[null]},"OptionalCallExpression":{"enter":[null]},"NewExpression":{"enter":[null]},"ImportSpecifier":{"enter":[null]},"ClassDeclaration":{"enter":[null]},"ClassExpression":{"enter":[null]},"FunctionDeclaration":{"enter":[null]},"FunctionExpression":{"enter":[null]},"ObjectMethod":{"enter":[null]},"ArrowFunctionExpression":{"enter":[null]},"ClassMethod":{"enter":[null]},"ClassPrivateMethod":{"enter":[null]},"AnyTypeAnnotation":{"enter":[null]},"ArrayTypeAnnotation":{"enter":[null]},"BooleanTypeAnnotation":{"enter":[null]},"BooleanLiteralTypeAnnotation":{"enter":[null]},"NullLiteralTypeAnnotation":{"enter":[null]},"ClassImplements":{"enter":[null]},"DeclareClass":{"enter":[null]},"DeclareFunction":{"enter":[null]},"DeclareInterface":{"enter":[null]},"DeclareModule":{"enter":[null]},"DeclareModuleExports":{"enter":[null]},"DeclareTypeAlias":{"enter":[null]},"DeclareOpaqueType":{"enter":[null]},"DeclareVariable":{"enter":[null]},"DeclareExportDeclaration":{"enter":[null]},"DeclareExportAllDeclaration":{"enter":[null]},"DeclaredPredicate":{"enter":[null]},"ExistsTypeAnnotation":{"enter":[null]},"FunctionTypeAnnotation":{"enter":[null]},"FunctionTypeParam":{"enter":[null]},"GenericTypeAnnotation":{"enter":[null]},"InferredPredicate":{"enter":[null]},"InterfaceExtends":{"enter":[null]},"InterfaceDeclaration":{"enter":[null]},"InterfaceTypeAnnotation":{"enter":[null]},"IntersectionTypeAnnotation":{"enter":[null]},"MixedTypeAnnotation":{"enter":[null]},"EmptyTypeAnnotation":{"enter":[null]},"NullableTypeAnnotation":{"enter":[null]},"NumberLiteralTypeAnnotation":{"enter":[null]},"NumberTypeAnnotation":{"enter":[null]},"ObjectTypeAnnotation":{"enter":[null]},"ObjectTypeInternalSlot":{"enter":[null]},"ObjectTypeCallProperty":{"enter":[null]},"ObjectTypeIndexer":{"enter":[null]},"ObjectTypeProperty":{"enter":[null]},"ObjectTypeSpreadProperty":{"enter":[null]},"OpaqueType":{"enter":[null]},"QualifiedTypeIdentifier":{"enter":[null]},"StringLiteralTypeAnnotation":{"enter":[null]},"StringTypeAnnotation":{"enter":[null]},"ThisTypeAnnotation":{"enter":[null]},"TupleTypeAnnotation":{"enter":[null]},"TypeofTypeAnnotation":{"enter":[null]},"TypeAlias":{"enter":[null]},"TypeAnnotation":{"enter":[null]},"TypeParameter":{"enter":[null]},"TypeParameterDeclaration":{"enter":[null]},"TypeParameterInstantiation":{"enter":[null]},"UnionTypeAnnotation":{"enter":[null]},"Variance":{"enter":[null]},"VoidTypeAnnotation":{"enter":[null]},"ExportAllDeclaration":{"enter":[null]},"ExportDefaultDeclaration":{"enter":[null]},"ExportNamedDeclaration":{"enter":[null]}},"options":{}},{"key":"transform-exponentiation-operator","visitor":{"AssignmentExpression":{"enter":[null]},"BinaryExpression":{"enter":[null]},"_exploded":true,"_verified":true},"options":{}},{"key":"proposal-async-generator-functions","visitor":{"_exploded":{},"_verified":{},"Program":{"enter":[null]}},"options":{}}],"presets":[],"generatorOpts":{"filename":"/Users/macbook/Desktop/Fedi/meteor/elearning/imports/ui/pages/new/new_post.jsx","comments":true,"compact":false,"sourceMaps":true,"sourceFileName":"imports/ui/pages/new/new_post.jsx"}},"code":"module.export({\n  default: () => New_Post\n});\nlet React, Component;\nmodule.link(\"react\", {\n  default(v) {\n    React = v;\n  },\n\n  Component(v) {\n    Component = v;\n  }\n\n}, 0);\nlet withHistory, Link;\nmodule.link(\"react-router-dom\", {\n  withHistory(v) {\n    withHistory = v;\n  },\n\n  Link(v) {\n    Link = v;\n  }\n\n}, 1);\nlet createContainer;\nmodule.link(\"meteor/react-meteor-data\", {\n  createContainer(v) {\n    createContainer = v;\n  }\n\n}, 2);\nlet Header;\nmodule.link(\"./header\", {\n  default(v) {\n    Header = v;\n  }\n\n}, 3);\nlet Footer;\nmodule.link(\"./footer\", {\n  default(v) {\n    Footer = v;\n  }\n\n}, 4);\n\nclass New_Post extends Component {\n  render() {\n    return React.createElement(\"div\", {\n      className: \"super_container\"\n    }, React.createElement(Header, null), React.createElement(\"div\", {\n      className: \"menu_container menu_mm\"\n    }, React.createElement(\"div\", {\n      className: \"menu_close_container\"\n    }, React.createElement(\"div\", {\n      className: \"menu_close\"\n    })), React.createElement(\"div\", {\n      className: \"menu_inner menu_mm\"\n    }, React.createElement(\"div\", {\n      className: \"menu menu_mm\"\n    }, React.createElement(\"ul\", {\n      className: \"menu_list menu_mm\"\n    }, React.createElement(\"li\", {\n      className: \"menu_item menu_mm\"\n    }, React.createElement(\"a\", {\n      href: \"index.html\"\n    }, \"Home\")), React.createElement(\"li\", {\n      className: \"menu_item menu_mm\"\n    }, React.createElement(\"a\", {\n      href: \"#\"\n    }, \"About us\")), React.createElement(\"li\", {\n      className: \"menu_item menu_mm\"\n    }, React.createElement(\"a\", {\n      href: \"courses.html\"\n    }, \"Courses\")), React.createElement(\"li\", {\n      className: \"menu_item menu_mm\"\n    }, React.createElement(\"a\", {\n      href: \"elements.html\"\n    }, \"Elements\")), React.createElement(\"li\", {\n      className: \"menu_item menu_mm\"\n    }, React.createElement(\"a\", {\n      href: \"news.html\"\n    }, \"News\")), React.createElement(\"li\", {\n      className: \"menu_item menu_mm\"\n    }, React.createElement(\"a\", {\n      href: \"contact.html\"\n    }, \"Contact\"))), React.createElement(\"div\", {\n      className: \"menu_social_container menu_mm\"\n    }, React.createElement(\"ul\", {\n      className: \"menu_social menu_mm\"\n    }, React.createElement(\"li\", {\n      className: \"menu_social_item menu_mm\"\n    }, React.createElement(\"a\", {\n      href: \"#\"\n    }, React.createElement(\"i\", {\n      className: \"fab fa-pinterest\"\n    }))), React.createElement(\"li\", {\n      className: \"menu_social_item menu_mm\"\n    }, React.createElement(\"a\", {\n      href: \"#\"\n    }, React.createElement(\"i\", {\n      className: \"fab fa-linkedin-in\"\n    }))), React.createElement(\"li\", {\n      className: \"menu_social_item menu_mm\"\n    }, React.createElement(\"a\", {\n      href: \"#\"\n    }, React.createElement(\"i\", {\n      className: \"fab fa-instagram\"\n    }))), React.createElement(\"li\", {\n      className: \"menu_social_item menu_mm\"\n    }, React.createElement(\"a\", {\n      href: \"#\"\n    }, React.createElement(\"i\", {\n      className: \"fab fa-facebook-f\"\n    }))), React.createElement(\"li\", {\n      className: \"menu_social_item menu_mm\"\n    }, React.createElement(\"a\", {\n      href: \"#\"\n    }, React.createElement(\"i\", {\n      className: \"fab fa-twitter\"\n    }))))), React.createElement(\"div\", {\n      className: \"menu_copyright menu_mm\"\n    }, \"Colorlib All rights reserved\")))), React.createElement(\"div\", {\n      className: \"home\"\n    }, React.createElement(\"div\", {\n      className: \"home_background_container prlx_parent\"\n    }, React.createElement(\"div\", {\n      className: \"home_background prlx\",\n      style: {\n        backgroundImage: \"url(images/news_background.jpg)\"\n      }\n    })), React.createElement(\"div\", {\n      className: \"home_content\"\n    }, React.createElement(\"h1\", null, \"The News\"))), React.createElement(\"div\", {\n      className: \"news\"\n    }, React.createElement(\"div\", {\n      className: \"container\"\n    }, React.createElement(\"div\", {\n      className: \"row\"\n    }, React.createElement(\"div\", {\n      className: \"col-lg-8\"\n    }, React.createElement(\"div\", {\n      className: \"news_post_container\"\n    }, React.createElement(\"div\", {\n      className: \"news_post\"\n    }, React.createElement(\"div\", {\n      className: \"news_post_image\"\n    }, React.createElement(\"img\", {\n      src: \"images/news_1.jpg\",\n      alt: \"https://unsplash.com/@dsmacinnes\"\n    })), React.createElement(\"div\", {\n      className: \"news_post_top d-flex flex-column flex-sm-row\"\n    }, React.createElement(\"div\", {\n      className: \"news_post_date_container\"\n    }, React.createElement(\"div\", {\n      className: \"news_post_date d-flex flex-column align-items-center justify-content-center\"\n    }, React.createElement(\"div\", null, \"18\"), React.createElement(\"div\", null, \"dec\"))), React.createElement(\"div\", {\n      className: \"news_post_title_container\"\n    }, React.createElement(\"div\", {\n      className: \"news_post_title\"\n    }, React.createElement(\"a\", {\n      href: \"news_post.html\"\n    }, \"Why do you need a qualification?\")), React.createElement(\"div\", {\n      className: \"news_post_meta\"\n    }, React.createElement(\"span\", {\n      className: \"news_post_author\"\n    }, React.createElement(\"a\", {\n      href: \"#\"\n    }, \"By Christian Smith\")), React.createElement(\"span\", null, \"|\"), React.createElement(\"span\", {\n      className: \"news_post_comments\"\n    }, React.createElement(\"a\", {\n      href: \"#\"\n    }, \"3 Comments\"))))), React.createElement(\"div\", {\n      className: \"news_post_text\"\n    }, React.createElement(\"p\", null, \"In aliquam, augue a gravida rutrum, ante nisl fermentum nulla, vitae tempor nisl ligula vel nunc. Proin quis mi malesuada, finibus tortor fermentum. Etiam eu purus nec eros varius luctus. Praesent finibus risus facilisis ultricies. Etiam eu purus nec eros varius luctus. Praesent finibus risus facilisis ultricies venenatis. Suspendisse fermentum sodales lacus, lacinia gravida elit dapibus sed. Cras in lectus elit. Maecenas tempus nunc vitae mi egestas venenatis. Aliquam rhoncus, purus in vehicula porttitor, lacus ante consequat purus, id elementum enim purus nec enim. In sed odio rhoncus, tristique ipsum id, pharetra neque.\", \" \")), React.createElement(\"div\", {\n      className: \"news_post_quote\"\n    }, React.createElement(\"p\", {\n      className: \"news_post_quote_text\"\n    }, React.createElement(\"span\", null, \"E\"), \"tiam eu purus nec eros varius luctus. Praesent finibus risus facilisis ultricies venena tis. Suspendisse fermentum sodales lacus, lacinia gravida elit.\")), React.createElement(\"p\", {\n      className: \"news_post_text\",\n      style: {\n        marginTop: 59\n      }\n    }, \"In aliquam, augue a gravida rutrum, ante nisl fermentum nulla, vitae tempor nisl ligula vel nunc. Proin quis mi malesuada, finibus tortor fermentum. Etiam eu purus nec eros varius luctus. Praesent finibus risus facilisis ultricies. Etiam eu purus nec eros varius luctus. Praesent finibus risus facilisis ultricies venenatis. Suspendisse fermentum sodales lacus, lacinia gravida elit dapibus sed. Cras in lectus elit. Maecenas tempus nunc vitae mi egestas venenatis. Aliquam rhoncus, purus in vehicula porttitor, lacus ante consequat purus, id elementum enim purus nec enim. In sed odio rhoncus, tristique ipsum id, pharetra neque.\", \" \"))), React.createElement(\"div\", {\n      className: \"news_post_comments\"\n    }, React.createElement(\"div\", {\n      className: \"comments_title\"\n    }, \"Comments\"), React.createElement(\"ul\", {\n      className: \"comments_list\"\n    }, React.createElement(\"li\", {\n      className: \"comment\"\n    }, React.createElement(\"div\", {\n      className: \"comment_container d-flex flex-row\"\n    }, React.createElement(\"div\", null, React.createElement(\"div\", {\n      className: \"comment_image\"\n    }, React.createElement(\"img\", {\n      src: \"images/comment_1.jpg\",\n      alt: true\n    }))), React.createElement(\"div\", {\n      className: \"comment_content\"\n    }, React.createElement(\"div\", {\n      className: \"comment_meta\"\n    }, React.createElement(\"span\", {\n      className: \"comment_name\"\n    }, React.createElement(\"a\", {\n      href: \"#\"\n    }, \"Mark Smith\")), React.createElement(\"span\", {\n      className: \"comment_separator\"\n    }, \"|\"), React.createElement(\"span\", {\n      className: \"comment_date\"\n    }, \"Dec 18, 2017\"), React.createElement(\"span\", {\n      className: \"comment_separator\"\n    }, \"|\"), React.createElement(\"span\", {\n      className: \"comment_reply_link\"\n    }, React.createElement(\"a\", {\n      href: \"#\"\n    }, \"Reply\"))), React.createElement(\"p\", {\n      className: \"comment_text\"\n    }, \"Aliquam rhoncus, purus in vehicula porttitor, lacus ante consequat purus, id elementum enim purus nec enim. In sed odio rhoncus, tristique ipsum id, pharetra neque.\", \" \")))), React.createElement(\"li\", {\n      className: \"comment\"\n    }, React.createElement(\"div\", {\n      className: \"comment_container d-flex flex-row\"\n    }, React.createElement(\"div\", null, React.createElement(\"div\", {\n      className: \"comment_image\"\n    }, React.createElement(\"img\", {\n      src: \"images/comment_2.jpg\",\n      alt: true\n    }))), React.createElement(\"div\", {\n      className: \"comment_content\"\n    }, React.createElement(\"div\", {\n      className: \"comment_meta\"\n    }, React.createElement(\"span\", {\n      className: \"comment_name\"\n    }, React.createElement(\"a\", {\n      href: \"#\"\n    }, \"Mark Smith\")), React.createElement(\"span\", {\n      className: \"comment_separator\"\n    }, \"|\"), React.createElement(\"span\", {\n      className: \"comment_date\"\n    }, \"Dec 18, 2017\"), React.createElement(\"span\", {\n      className: \"comment_separator\"\n    }, \"|\"), React.createElement(\"span\", {\n      className: \"comment_reply_link\"\n    }, React.createElement(\"a\", {\n      href: \"#\"\n    }, \"Reply\"))), React.createElement(\"p\", {\n      className: \"comment_text\"\n    }, \"Aliquam rhoncus, purus in vehicula porttitor, lacus ante consequat purus, id elementum enim purus nec enim. In sed odio rhoncus, tristique ipsum id, pharetra neque.\", \" \")))))), React.createElement(\"div\", {\n      className: \"leave_comment\"\n    }, React.createElement(\"div\", {\n      className: \"leave_comment_title\"\n    }, \"Leave a comment\"), React.createElement(\"div\", {\n      className: \"leave_comment_form_container\"\n    }, React.createElement(\"form\", {\n      action: \"post\"\n    }, React.createElement(\"input\", {\n      id: \"comment_form_name\",\n      className: \"input_field contact_form_name\",\n      type: \"text\",\n      placeholder: \"Name\",\n      required: \"required\",\n      \"data-error\": \"Name is required.\"\n    }), React.createElement(\"input\", {\n      id: \"comment_form_email\",\n      className: \"input_field contact_form_email\",\n      type: \"email\",\n      placeholder: \"E-mail\",\n      required: \"required\",\n      \"data-error\": \"Valid email is required.\"\n    }), React.createElement(\"textarea\", {\n      id: \"comment_form_message\",\n      className: \"text_field contact_form_message\",\n      name: \"message\",\n      placeholder: \"Message\",\n      required: \"required\",\n      \"data-error\": \"Please, write us a message.\",\n      defaultValue: \"\"\n    }), React.createElement(\"button\", {\n      id: \"comment_send_btn\",\n      type: \"submit\",\n      className: \"comment_send_btn trans_200\",\n      value: \"Submit\"\n    }, \"send message\"))))), React.createElement(\"div\", {\n      className: \"col-lg-4\"\n    }, React.createElement(\"div\", {\n      className: \"sidebar\"\n    }, React.createElement(\"div\", {\n      className: \"sidebar_section\"\n    }, React.createElement(\"div\", {\n      className: \"sidebar_section_title\"\n    }, React.createElement(\"h3\", null, \"Archives\")), React.createElement(\"ul\", {\n      className: \"sidebar_list\"\n    }, React.createElement(\"li\", {\n      className: \"sidebar_list_item\"\n    }, React.createElement(\"a\", {\n      href: \"#\"\n    }, \"Design Courses\")), React.createElement(\"li\", {\n      className: \"sidebar_list_item\"\n    }, React.createElement(\"a\", {\n      href: \"#\"\n    }, \"All you need to know\")), React.createElement(\"li\", {\n      className: \"sidebar_list_item\"\n    }, React.createElement(\"a\", {\n      href: \"#\"\n    }, \"Uncategorized\")), React.createElement(\"li\", {\n      className: \"sidebar_list_item\"\n    }, React.createElement(\"a\", {\n      href: \"#\"\n    }, \"About Our Departments\")), React.createElement(\"li\", {\n      className: \"sidebar_list_item\"\n    }, React.createElement(\"a\", {\n      href: \"#\"\n    }, \"Choose the right course\")))), React.createElement(\"div\", {\n      className: \"sidebar_section\"\n    }, React.createElement(\"div\", {\n      className: \"sidebar_section_title\"\n    }, React.createElement(\"h3\", null, \"Latest posts\")), React.createElement(\"div\", {\n      className: \"latest_posts\"\n    }, React.createElement(\"div\", {\n      className: \"latest_post\"\n    }, React.createElement(\"div\", {\n      className: \"latest_post_image\"\n    }, React.createElement(\"img\", {\n      src: \"images/latest_1.jpg\",\n      alt: \"https://unsplash.com/@dsmacinnes\"\n    })), React.createElement(\"div\", {\n      className: \"latest_post_title\"\n    }, React.createElement(\"a\", {\n      href: \"news_post.html\"\n    }, \"Why do you need a qualification?\")), React.createElement(\"div\", {\n      className: \"latest_post_meta\"\n    }, React.createElement(\"span\", {\n      className: \"latest_post_author\"\n    }, React.createElement(\"a\", {\n      href: \"#\"\n    }, \"By Christian Smith\")), React.createElement(\"span\", null, \"|\"), React.createElement(\"span\", {\n      className: \"latest_post_comments\"\n    }, React.createElement(\"a\", {\n      href: \"#\"\n    }, \"3 Comments\")))), React.createElement(\"div\", {\n      className: \"latest_post\"\n    }, React.createElement(\"div\", {\n      className: \"latest_post_image\"\n    }, React.createElement(\"img\", {\n      src: \"images/latest_2.jpg\",\n      alt: \"https://unsplash.com/@erothermel\"\n    })), React.createElement(\"div\", {\n      className: \"latest_post_title\"\n    }, React.createElement(\"a\", {\n      href: \"news_post.html\"\n    }, \"Why do you need a qualification?\")), React.createElement(\"div\", {\n      className: \"latest_post_meta\"\n    }, React.createElement(\"span\", {\n      className: \"latest_post_author\"\n    }, React.createElement(\"a\", {\n      href: \"#\"\n    }, \"By Christian Smith\")), React.createElement(\"span\", null, \"|\"), React.createElement(\"span\", {\n      className: \"latest_post_comments\"\n    }, React.createElement(\"a\", {\n      href: \"#\"\n    }, \"3 Comments\")))), React.createElement(\"div\", {\n      className: \"latest_post\"\n    }, React.createElement(\"div\", {\n      className: \"latest_post_image\"\n    }, React.createElement(\"img\", {\n      src: \"images/latest_3.jpg\",\n      alt: \"https://unsplash.com/@element5digital\"\n    })), React.createElement(\"div\", {\n      className: \"latest_post_title\"\n    }, React.createElement(\"a\", {\n      href: \"news_post.html\"\n    }, \"Why do you need a qualification?\")), React.createElement(\"div\", {\n      className: \"latest_post_meta\"\n    }, React.createElement(\"span\", {\n      className: \"latest_post_author\"\n    }, React.createElement(\"a\", {\n      href: \"#\"\n    }, \"By Christian Smith\")), React.createElement(\"span\", null, \"|\"), React.createElement(\"span\", {\n      className: \"latest_post_comments\"\n    }, React.createElement(\"a\", {\n      href: \"#\"\n    }, \"3 Comments\")))))), React.createElement(\"div\", {\n      className: \"sidebar_section\"\n    }, React.createElement(\"div\", {\n      className: \"sidebar_section_title\"\n    }, React.createElement(\"h3\", null, \"Tags\")), React.createElement(\"div\", {\n      className: \"tags d-flex flex-row flex-wrap\"\n    }, React.createElement(\"div\", {\n      className: \"tag\"\n    }, React.createElement(\"a\", {\n      href: \"#\"\n    }, \"Course\")), React.createElement(\"div\", {\n      className: \"tag\"\n    }, React.createElement(\"a\", {\n      href: \"#\"\n    }, \"Design\")), React.createElement(\"div\", {\n      className: \"tag\"\n    }, React.createElement(\"a\", {\n      href: \"#\"\n    }, \"FAQ\")), React.createElement(\"div\", {\n      className: \"tag\"\n    }, React.createElement(\"a\", {\n      href: \"#\"\n    }, \"Teachers\")), React.createElement(\"div\", {\n      className: \"tag\"\n    }, React.createElement(\"a\", {\n      href: \"#\"\n    }, \"School\")), React.createElement(\"div\", {\n      className: \"tag\"\n    }, React.createElement(\"a\", {\n      href: \"#\"\n    }, \"Graduate\"))))))))), React.createElement(Footer, null));\n  }\n\n}","map":{"version":3,"sources":["imports/ui/pages/new/new_post.jsx"],"names":["module","export","default","New_Post","React","Component","link","v","withHistory","Link","createContainer","Header","Footer","render","backgroundImage","marginTop"],"mappings":"AAAAA,MAAM,CAACC,MAAP,CAAc;AAACC,EAAAA,OAAO,EAAC,MAAIC;AAAb,CAAd;AAAsC,IAAIC,KAAJ,EAAUC,SAAV;AAAoBL,MAAM,CAACM,IAAP,CAAY,OAAZ,EAAoB;AAACJ,EAAAA,OAAO,CAACK,CAAD,EAAG;AAACH,IAAAA,KAAK,GAACG,CAAN;AAAQ,GAApB;;AAAqBF,EAAAA,SAAS,CAACE,CAAD,EAAG;AAACF,IAAAA,SAAS,GAACE,CAAV;AAAY;;AAA9C,CAApB,EAAoE,CAApE;AAAuE,IAAIC,WAAJ,EAAgBC,IAAhB;AAAqBT,MAAM,CAACM,IAAP,CAAY,kBAAZ,EAA+B;AAACE,EAAAA,WAAW,CAACD,CAAD,EAAG;AAACC,IAAAA,WAAW,GAACD,CAAZ;AAAc,GAA9B;;AAA+BE,EAAAA,IAAI,CAACF,CAAD,EAAG;AAACE,IAAAA,IAAI,GAACF,CAAL;AAAO;;AAA9C,CAA/B,EAA+E,CAA/E;AAAkF,IAAIG,eAAJ;AAAoBV,MAAM,CAACM,IAAP,CAAY,0BAAZ,EAAuC;AAACI,EAAAA,eAAe,CAACH,CAAD,EAAG;AAACG,IAAAA,eAAe,GAACH,CAAhB;AAAkB;;AAAtC,CAAvC,EAA+E,CAA/E;AAAkF,IAAII,MAAJ;AAAWX,MAAM,CAACM,IAAP,CAAY,UAAZ,EAAuB;AAACJ,EAAAA,OAAO,CAACK,CAAD,EAAG;AAACI,IAAAA,MAAM,GAACJ,CAAP;AAAS;;AAArB,CAAvB,EAA8C,CAA9C;AAAiD,IAAIK,MAAJ;AAAWZ,MAAM,CAACM,IAAP,CAAY,UAAZ,EAAuB;AAACJ,EAAAA,OAAO,CAACK,CAAD,EAAG;AAACK,IAAAA,MAAM,GAACL,CAAP;AAAS;;AAArB,CAAvB,EAA8C,CAA9C;;AAMtY,MAAMJ,QAAN,SAAuBE,SAAvB,CAAiC;AAG9CQ,EAAAA,MAAM,GAAE;AACN,WAEE;AAAK,MAAA,SAAS,EAAC;AAAf,OAEE,oBAAC,MAAD,OAFF,EAIE;AAAK,MAAA,SAAS,EAAC;AAAf,OAEE;AAAK,MAAA,SAAS,EAAC;AAAf,OACE;AAAK,MAAA,SAAS,EAAC;AAAf,MADF,CAFF,EAME;AAAK,MAAA,SAAS,EAAC;AAAf,OACE;AAAK,MAAA,SAAS,EAAC;AAAf,OACE;AAAI,MAAA,SAAS,EAAC;AAAd,OACE;AAAI,MAAA,SAAS,EAAC;AAAd,OACE;AAAG,MAAA,IAAI,EAAC;AAAR,cADF,CADF,EAIE;AAAI,MAAA,SAAS,EAAC;AAAd,OACE;AAAG,MAAA,IAAI,EAAC;AAAR,kBADF,CAJF,EAOE;AAAI,MAAA,SAAS,EAAC;AAAd,OACE;AAAG,MAAA,IAAI,EAAC;AAAR,iBADF,CAPF,EAUE;AAAI,MAAA,SAAS,EAAC;AAAd,OACE;AAAG,MAAA,IAAI,EAAC;AAAR,kBADF,CAVF,EAaE;AAAI,MAAA,SAAS,EAAC;AAAd,OACE;AAAG,MAAA,IAAI,EAAC;AAAR,cADF,CAbF,EAgBE;AAAI,MAAA,SAAS,EAAC;AAAd,OACE;AAAG,MAAA,IAAI,EAAC;AAAR,iBADF,CAhBF,CADF,EAsBE;AAAK,MAAA,SAAS,EAAC;AAAf,OACE;AAAI,MAAA,SAAS,EAAC;AAAd,OACE;AAAI,MAAA,SAAS,EAAC;AAAd,OACE;AAAG,MAAA,IAAI,EAAC;AAAR,OACE;AAAG,MAAA,SAAS,EAAC;AAAb,MADF,CADF,CADF,EAME;AAAI,MAAA,SAAS,EAAC;AAAd,OACE;AAAG,MAAA,IAAI,EAAC;AAAR,OACE;AAAG,MAAA,SAAS,EAAC;AAAb,MADF,CADF,CANF,EAWE;AAAI,MAAA,SAAS,EAAC;AAAd,OACE;AAAG,MAAA,IAAI,EAAC;AAAR,OACE;AAAG,MAAA,SAAS,EAAC;AAAb,MADF,CADF,CAXF,EAgBE;AAAI,MAAA,SAAS,EAAC;AAAd,OACE;AAAG,MAAA,IAAI,EAAC;AAAR,OACE;AAAG,MAAA,SAAS,EAAC;AAAb,MADF,CADF,CAhBF,EAqBE;AAAI,MAAA,SAAS,EAAC;AAAd,OACE;AAAG,MAAA,IAAI,EAAC;AAAR,OACE;AAAG,MAAA,SAAS,EAAC;AAAb,MADF,CADF,CArBF,CADF,CAtBF,EAmDE;AAAK,MAAA,SAAS,EAAC;AAAf,sCAnDF,CADF,CANF,CAJF,EAqEE;AAAK,MAAA,SAAS,EAAC;AAAf,OACE;AAAK,MAAA,SAAS,EAAC;AAAf,OACE;AACE,MAAA,SAAS,EAAC,sBADZ;AAEE,MAAA,KAAK,EAAE;AAAEC,QAAAA,eAAe,EAAE;AAAnB;AAFT,MADF,CADF,EAOE;AAAK,MAAA,SAAS,EAAC;AAAf,OACE,2CADF,CAPF,CArEF,EAiFE;AAAK,MAAA,SAAS,EAAC;AAAf,OACE;AAAK,MAAA,SAAS,EAAC;AAAf,OACE;AAAK,MAAA,SAAS,EAAC;AAAf,OAEE;AAAK,MAAA,SAAS,EAAC;AAAf,OACE;AAAK,MAAA,SAAS,EAAC;AAAf,OAEE;AAAK,MAAA,SAAS,EAAC;AAAf,OACE;AAAK,MAAA,SAAS,EAAC;AAAf,OACE;AACE,MAAA,GAAG,EAAC,mBADN;AAEE,MAAA,GAAG,EAAC;AAFN,MADF,CADF,EAOE;AAAK,MAAA,SAAS,EAAC;AAAf,OACE;AAAK,MAAA,SAAS,EAAC;AAAf,OACE;AAAK,MAAA,SAAS,EAAC;AAAf,OACE,sCADF,EAEE,uCAFF,CADF,CADF,EAOE;AAAK,MAAA,SAAS,EAAC;AAAf,OACE;AAAK,MAAA,SAAS,EAAC;AAAf,OACE;AAAG,MAAA,IAAI,EAAC;AAAR,0CADF,CADF,EAME;AAAK,MAAA,SAAS,EAAC;AAAf,OACE;AAAM,MAAA,SAAS,EAAC;AAAhB,OACE;AAAG,MAAA,IAAI,EAAC;AAAR,4BADF,CADF,EAIE,sCAJF,EAKE;AAAM,MAAA,SAAS,EAAC;AAAhB,OACE;AAAG,MAAA,IAAI,EAAC;AAAR,oBADF,CALF,CANF,CAPF,CAPF,EA+BE;AAAK,MAAA,SAAS,EAAC;AAAf,OACE,ypBAa4B,GAb5B,CADF,CA/BF,EAgDE;AAAK,MAAA,SAAS,EAAC;AAAf,OACE;AAAG,MAAA,SAAS,EAAC;AAAb,OACE,sCADF,4JADF,CAhDF,EAwDE;AAAG,MAAA,SAAS,EAAC,gBAAb;AAA8B,MAAA,KAAK,EAAE;AAAEC,QAAAA,SAAS,EAAE;AAAb;AAArC,ioBAYsC,GAZtC,CAxDF,CAFF,CADF,EA4EE;AAAK,MAAA,SAAS,EAAC;AAAf,OACE;AAAK,MAAA,SAAS,EAAC;AAAf,kBADF,EAEE;AAAI,MAAA,SAAS,EAAC;AAAd,OAEE;AAAI,MAAA,SAAS,EAAC;AAAd,OACE;AAAK,MAAA,SAAS,EAAC;AAAf,OACE,iCACE;AAAK,MAAA,SAAS,EAAC;AAAf,OACE;AAAK,MAAA,GAAG,EAAC,sBAAT;AAAgC,MAAA,GAAG;AAAnC,MADF,CADF,CADF,EAME;AAAK,MAAA,SAAS,EAAC;AAAf,OACE;AAAK,MAAA,SAAS,EAAC;AAAf,OACE;AAAM,MAAA,SAAS,EAAC;AAAhB,OACE;AAAG,MAAA,IAAI,EAAC;AAAR,oBADF,CADF,EAIE;AAAM,MAAA,SAAS,EAAC;AAAhB,WAJF,EAKE;AAAM,MAAA,SAAS,EAAC;AAAhB,sBALF,EAME;AAAM,MAAA,SAAS,EAAC;AAAhB,WANF,EAOE;AAAM,MAAA,SAAS,EAAC;AAAhB,OACE;AAAG,MAAA,IAAI,EAAC;AAAR,eADF,CAPF,CADF,EAYE;AAAG,MAAA,SAAS,EAAC;AAAb,+KAI4B,GAJ5B,CAZF,CANF,CADF,CAFF,EA+BE;AAAI,MAAA,SAAS,EAAC;AAAd,OACE;AAAK,MAAA,SAAS,EAAC;AAAf,OACE,iCACE;AAAK,MAAA,SAAS,EAAC;AAAf,OACE;AAAK,MAAA,GAAG,EAAC,sBAAT;AAAgC,MAAA,GAAG;AAAnC,MADF,CADF,CADF,EAME;AAAK,MAAA,SAAS,EAAC;AAAf,OACE;AAAK,MAAA,SAAS,EAAC;AAAf,OACE;AAAM,MAAA,SAAS,EAAC;AAAhB,OACE;AAAG,MAAA,IAAI,EAAC;AAAR,oBADF,CADF,EAIE;AAAM,MAAA,SAAS,EAAC;AAAhB,WAJF,EAKE;AAAM,MAAA,SAAS,EAAC;AAAhB,sBALF,EAME;AAAM,MAAA,SAAS,EAAC;AAAhB,WANF,EAOE;AAAM,MAAA,SAAS,EAAC;AAAhB,OACE;AAAG,MAAA,IAAI,EAAC;AAAR,eADF,CAPF,CADF,EAYE;AAAG,MAAA,SAAS,EAAC;AAAb,+KAI4B,GAJ5B,CAZF,CANF,CADF,CA/BF,CAFF,CA5EF,EA4IE;AAAK,MAAA,SAAS,EAAC;AAAf,OACE;AAAK,MAAA,SAAS,EAAC;AAAf,yBADF,EAEE;AAAK,MAAA,SAAS,EAAC;AAAf,OACE;AAAM,MAAA,MAAM,EAAC;AAAb,OACE;AACE,MAAA,EAAE,EAAC,mBADL;AAEE,MAAA,SAAS,EAAC,+BAFZ;AAGE,MAAA,IAAI,EAAC,MAHP;AAIE,MAAA,WAAW,EAAC,MAJd;AAKE,MAAA,QAAQ,EAAC,UALX;AAME,oBAAW;AANb,MADF,EASE;AACE,MAAA,EAAE,EAAC,oBADL;AAEE,MAAA,SAAS,EAAC,gCAFZ;AAGE,MAAA,IAAI,EAAC,OAHP;AAIE,MAAA,WAAW,EAAC,QAJd;AAKE,MAAA,QAAQ,EAAC,UALX;AAME,oBAAW;AANb,MATF,EAiBE;AACE,MAAA,EAAE,EAAC,sBADL;AAEE,MAAA,SAAS,EAAC,iCAFZ;AAGE,MAAA,IAAI,EAAC,SAHP;AAIE,MAAA,WAAW,EAAC,SAJd;AAKE,MAAA,QAAQ,EAAC,UALX;AAME,oBAAW,6BANb;AAOE,MAAA,YAAY,EAAE;AAPhB,MAjBF,EA0BE;AACE,MAAA,EAAE,EAAC,kBADL;AAEE,MAAA,IAAI,EAAC,QAFP;AAGE,MAAA,SAAS,EAAC,4BAHZ;AAIE,MAAA,KAAK,EAAC;AAJR,sBA1BF,CADF,CAFF,CA5IF,CAFF,EAwLE;AAAK,MAAA,SAAS,EAAC;AAAf,OACE;AAAK,MAAA,SAAS,EAAC;AAAf,OAEE;AAAK,MAAA,SAAS,EAAC;AAAf,OACE;AAAK,MAAA,SAAS,EAAC;AAAf,OACE,2CADF,CADF,EAIE;AAAI,MAAA,SAAS,EAAC;AAAd,OACE;AAAI,MAAA,SAAS,EAAC;AAAd,OACE;AAAG,MAAA,IAAI,EAAC;AAAR,wBADF,CADF,EAIE;AAAI,MAAA,SAAS,EAAC;AAAd,OACE;AAAG,MAAA,IAAI,EAAC;AAAR,8BADF,CAJF,EAOE;AAAI,MAAA,SAAS,EAAC;AAAd,OACE;AAAG,MAAA,IAAI,EAAC;AAAR,uBADF,CAPF,EAUE;AAAI,MAAA,SAAS,EAAC;AAAd,OACE;AAAG,MAAA,IAAI,EAAC;AAAR,+BADF,CAVF,EAaE;AAAI,MAAA,SAAS,EAAC;AAAd,OACE;AAAG,MAAA,IAAI,EAAC;AAAR,iCADF,CAbF,CAJF,CAFF,EAyBE;AAAK,MAAA,SAAS,EAAC;AAAf,OACE;AAAK,MAAA,SAAS,EAAC;AAAf,OACE,+CADF,CADF,EAIE;AAAK,MAAA,SAAS,EAAC;AAAf,OAEE;AAAK,MAAA,SAAS,EAAC;AAAf,OACE;AAAK,MAAA,SAAS,EAAC;AAAf,OACE;AACE,MAAA,GAAG,EAAC,qBADN;AAEE,MAAA,GAAG,EAAC;AAFN,MADF,CADF,EAOE;AAAK,MAAA,SAAS,EAAC;AAAf,OACE;AAAG,MAAA,IAAI,EAAC;AAAR,0CADF,CAPF,EAYE;AAAK,MAAA,SAAS,EAAC;AAAf,OACE;AAAM,MAAA,SAAS,EAAC;AAAhB,OACE;AAAG,MAAA,IAAI,EAAC;AAAR,4BADF,CADF,EAIE,sCAJF,EAKE;AAAM,MAAA,SAAS,EAAC;AAAhB,OACE;AAAG,MAAA,IAAI,EAAC;AAAR,oBADF,CALF,CAZF,CAFF,EAyBE;AAAK,MAAA,SAAS,EAAC;AAAf,OACE;AAAK,MAAA,SAAS,EAAC;AAAf,OACE;AACE,MAAA,GAAG,EAAC,qBADN;AAEE,MAAA,GAAG,EAAC;AAFN,MADF,CADF,EAOE;AAAK,MAAA,SAAS,EAAC;AAAf,OACE;AAAG,MAAA,IAAI,EAAC;AAAR,0CADF,CAPF,EAYE;AAAK,MAAA,SAAS,EAAC;AAAf,OACE;AAAM,MAAA,SAAS,EAAC;AAAhB,OACE;AAAG,MAAA,IAAI,EAAC;AAAR,4BADF,CADF,EAIE,sCAJF,EAKE;AAAM,MAAA,SAAS,EAAC;AAAhB,OACE;AAAG,MAAA,IAAI,EAAC;AAAR,oBADF,CALF,CAZF,CAzBF,EAgDE;AAAK,MAAA,SAAS,EAAC;AAAf,OACE;AAAK,MAAA,SAAS,EAAC;AAAf,OACE;AACE,MAAA,GAAG,EAAC,qBADN;AAEE,MAAA,GAAG,EAAC;AAFN,MADF,CADF,EAOE;AAAK,MAAA,SAAS,EAAC;AAAf,OACE;AAAG,MAAA,IAAI,EAAC;AAAR,0CADF,CAPF,EAYE;AAAK,MAAA,SAAS,EAAC;AAAf,OACE;AAAM,MAAA,SAAS,EAAC;AAAhB,OACE;AAAG,MAAA,IAAI,EAAC;AAAR,4BADF,CADF,EAIE,sCAJF,EAKE;AAAM,MAAA,SAAS,EAAC;AAAhB,OACE;AAAG,MAAA,IAAI,EAAC;AAAR,oBADF,CALF,CAZF,CAhDF,CAJF,CAzBF,EAsGE;AAAK,MAAA,SAAS,EAAC;AAAf,OACE;AAAK,MAAA,SAAS,EAAC;AAAf,OACE,uCADF,CADF,EAIE;AAAK,MAAA,SAAS,EAAC;AAAf,OACE;AAAK,MAAA,SAAS,EAAC;AAAf,OACE;AAAG,MAAA,IAAI,EAAC;AAAR,gBADF,CADF,EAIE;AAAK,MAAA,SAAS,EAAC;AAAf,OACE;AAAG,MAAA,IAAI,EAAC;AAAR,gBADF,CAJF,EAOE;AAAK,MAAA,SAAS,EAAC;AAAf,OACE;AAAG,MAAA,IAAI,EAAC;AAAR,aADF,CAPF,EAUE;AAAK,MAAA,SAAS,EAAC;AAAf,OACE;AAAG,MAAA,IAAI,EAAC;AAAR,kBADF,CAVF,EAaE;AAAK,MAAA,SAAS,EAAC;AAAf,OACE;AAAG,MAAA,IAAI,EAAC;AAAR,gBADF,CAbF,EAgBE;AAAK,MAAA,SAAS,EAAC;AAAf,OACE;AAAG,MAAA,IAAI,EAAC;AAAR,kBADF,CAhBF,CAJF,CAtGF,CADF,CAxLF,CADF,CADF,CAjFF,EAiZE,oBAAC,MAAD,OAjZF,CAFF;AAwZD;;AA5Z6C","sourcesContent":["import React, { Component } from 'react'\nimport { withHistory, Link } from 'react-router-dom'\nimport { createContainer } from 'meteor/react-meteor-data'\nimport Header from './header';\nimport Footer from './footer';\n\nexport default class New_Post extends Component {\n\n\n  render(){\n    return (\n\n      <div className=\"super_container\">\n      \n        <Header/>\n\n        <div className=\"menu_container menu_mm\">\n          {/* Menu Close Button */}\n          <div className=\"menu_close_container\">\n            <div className=\"menu_close\" />\n          </div>\n          {/* Menu Items */}\n          <div className=\"menu_inner menu_mm\">\n            <div className=\"menu menu_mm\">\n              <ul className=\"menu_list menu_mm\">\n                <li className=\"menu_item menu_mm\">\n                  <a href=\"index.html\">Home</a>\n                </li>\n                <li className=\"menu_item menu_mm\">\n                  <a href=\"#\">About us</a>\n                </li>\n                <li className=\"menu_item menu_mm\">\n                  <a href=\"courses.html\">Courses</a>\n                </li>\n                <li className=\"menu_item menu_mm\">\n                  <a href=\"elements.html\">Elements</a>\n                </li>\n                <li className=\"menu_item menu_mm\">\n                  <a href=\"news.html\">News</a>\n                </li>\n                <li className=\"menu_item menu_mm\">\n                  <a href=\"contact.html\">Contact</a>\n                </li>\n              </ul>\n              {/* Menu Social */}\n              <div className=\"menu_social_container menu_mm\">\n                <ul className=\"menu_social menu_mm\">\n                  <li className=\"menu_social_item menu_mm\">\n                    <a href=\"#\">\n                      <i className=\"fab fa-pinterest\" />\n                    </a>\n                  </li>\n                  <li className=\"menu_social_item menu_mm\">\n                    <a href=\"#\">\n                      <i className=\"fab fa-linkedin-in\" />\n                    </a>\n                  </li>\n                  <li className=\"menu_social_item menu_mm\">\n                    <a href=\"#\">\n                      <i className=\"fab fa-instagram\" />\n                    </a>\n                  </li>\n                  <li className=\"menu_social_item menu_mm\">\n                    <a href=\"#\">\n                      <i className=\"fab fa-facebook-f\" />\n                    </a>\n                  </li>\n                  <li className=\"menu_social_item menu_mm\">\n                    <a href=\"#\">\n                      <i className=\"fab fa-twitter\" />\n                    </a>\n                  </li>\n                </ul>\n              </div>\n              <div className=\"menu_copyright menu_mm\">\n                Colorlib All rights reserved\n              </div>\n            </div>\n          </div>\n        </div>\n\n        <div className=\"home\">\n          <div className=\"home_background_container prlx_parent\">\n            <div\n              className=\"home_background prlx\"\n              style={{ backgroundImage: \"url(images/news_background.jpg)\" }}\n            />\n          </div>\n          <div className=\"home_content\">\n            <h1>The News</h1>\n          </div>\n        </div>\n\n        <div className=\"news\">\n          <div className=\"container\">\n            <div className=\"row\">\n              {/* News Post Column */}\n              <div className=\"col-lg-8\">\n                <div className=\"news_post_container\">\n                  {/* News Post */}\n                  <div className=\"news_post\">\n                    <div className=\"news_post_image\">\n                      <img\n                        src=\"images/news_1.jpg\"\n                        alt=\"https://unsplash.com/@dsmacinnes\"\n                      />\n                    </div>\n                    <div className=\"news_post_top d-flex flex-column flex-sm-row\">\n                      <div className=\"news_post_date_container\">\n                        <div className=\"news_post_date d-flex flex-column align-items-center justify-content-center\">\n                          <div>18</div>\n                          <div>dec</div>\n                        </div>\n                      </div>\n                      <div className=\"news_post_title_container\">\n                        <div className=\"news_post_title\">\n                          <a href=\"news_post.html\">\n                            Why do you need a qualification?\n                          </a>\n                        </div>\n                        <div className=\"news_post_meta\">\n                          <span className=\"news_post_author\">\n                            <a href=\"#\">By Christian Smith</a>\n                          </span>\n                          <span>|</span>\n                          <span className=\"news_post_comments\">\n                            <a href=\"#\">3 Comments</a>\n                          </span>\n                        </div>\n                      </div>\n                    </div>\n                    <div className=\"news_post_text\">\n                      <p>\n                        In aliquam, augue a gravida rutrum, ante nisl\n                        fermentum nulla, vitae tempor nisl ligula vel nunc.\n                        Proin quis mi malesuada, finibus tortor fermentum.\n                        Etiam eu purus nec eros varius luctus. Praesent\n                        finibus risus facilisis ultricies. Etiam eu purus nec\n                        eros varius luctus. Praesent finibus risus facilisis\n                        ultricies venenatis. Suspendisse fermentum sodales\n                        lacus, lacinia gravida elit dapibus sed. Cras in\n                        lectus elit. Maecenas tempus nunc vitae mi egestas\n                        venenatis. Aliquam rhoncus, purus in vehicula\n                        porttitor, lacus ante consequat purus, id elementum\n                        enim purus nec enim. In sed odio rhoncus, tristique\n                        ipsum id, pharetra neque.{\" \"}\n                      </p>\n                    </div>\n                    <div className=\"news_post_quote\">\n                      <p className=\"news_post_quote_text\">\n                        <span>E</span>tiam eu purus nec eros varius luctus.\n                        Praesent finibus risus facilisis ultricies venena tis.\n                        Suspendisse fermentum sodales lacus, lacinia gravida\n                        elit.\n                      </p>\n                    </div>\n                    <p className=\"news_post_text\" style={{ marginTop: 59 }}>\n                      In aliquam, augue a gravida rutrum, ante nisl fermentum\n                      nulla, vitae tempor nisl ligula vel nunc. Proin quis mi\n                      malesuada, finibus tortor fermentum. Etiam eu purus nec\n                      eros varius luctus. Praesent finibus risus facilisis\n                      ultricies. Etiam eu purus nec eros varius luctus.\n                      Praesent finibus risus facilisis ultricies venenatis.\n                      Suspendisse fermentum sodales lacus, lacinia gravida\n                      elit dapibus sed. Cras in lectus elit. Maecenas tempus\n                      nunc vitae mi egestas venenatis. Aliquam rhoncus, purus\n                      in vehicula porttitor, lacus ante consequat purus, id\n                      elementum enim purus nec enim. In sed odio rhoncus,\n                      tristique ipsum id, pharetra neque.{\" \"}\n                    </p>\n                  </div>\n                </div>\n                {/* Comments */}\n                <div className=\"news_post_comments\">\n                  <div className=\"comments_title\">Comments</div>\n                  <ul className=\"comments_list\">\n                    {/* Comment */}\n                    <li className=\"comment\">\n                      <div className=\"comment_container d-flex flex-row\">\n                        <div>\n                          <div className=\"comment_image\">\n                            <img src=\"images/comment_1.jpg\" alt />\n                          </div>\n                        </div>\n                        <div className=\"comment_content\">\n                          <div className=\"comment_meta\">\n                            <span className=\"comment_name\">\n                              <a href=\"#\">Mark Smith</a>\n                            </span>\n                            <span className=\"comment_separator\">|</span>\n                            <span className=\"comment_date\">Dec 18, 2017</span>\n                            <span className=\"comment_separator\">|</span>\n                            <span className=\"comment_reply_link\">\n                              <a href=\"#\">Reply</a>\n                            </span>\n                          </div>\n                          <p className=\"comment_text\">\n                            Aliquam rhoncus, purus in vehicula porttitor,\n                            lacus ante consequat purus, id elementum enim\n                            purus nec enim. In sed odio rhoncus, tristique\n                            ipsum id, pharetra neque.{\" \"}\n                          </p>\n                        </div>\n                      </div>\n                    </li>\n                    {/* Comment */}\n                    <li className=\"comment\">\n                      <div className=\"comment_container d-flex flex-row\">\n                        <div>\n                          <div className=\"comment_image\">\n                            <img src=\"images/comment_2.jpg\" alt />\n                          </div>\n                        </div>\n                        <div className=\"comment_content\">\n                          <div className=\"comment_meta\">\n                            <span className=\"comment_name\">\n                              <a href=\"#\">Mark Smith</a>\n                            </span>\n                            <span className=\"comment_separator\">|</span>\n                            <span className=\"comment_date\">Dec 18, 2017</span>\n                            <span className=\"comment_separator\">|</span>\n                            <span className=\"comment_reply_link\">\n                              <a href=\"#\">Reply</a>\n                            </span>\n                          </div>\n                          <p className=\"comment_text\">\n                            Aliquam rhoncus, purus in vehicula porttitor,\n                            lacus ante consequat purus, id elementum enim\n                            purus nec enim. In sed odio rhoncus, tristique\n                            ipsum id, pharetra neque.{\" \"}\n                          </p>\n                        </div>\n                      </div>\n                    </li>\n                  </ul>\n                </div>\n                {/* Leave Comment */}\n                <div className=\"leave_comment\">\n                  <div className=\"leave_comment_title\">Leave a comment</div>\n                  <div className=\"leave_comment_form_container\">\n                    <form action=\"post\">\n                      <input\n                        id=\"comment_form_name\"\n                        className=\"input_field contact_form_name\"\n                        type=\"text\"\n                        placeholder=\"Name\"\n                        required=\"required\"\n                        data-error=\"Name is required.\"\n                      />\n                      <input\n                        id=\"comment_form_email\"\n                        className=\"input_field contact_form_email\"\n                        type=\"email\"\n                        placeholder=\"E-mail\"\n                        required=\"required\"\n                        data-error=\"Valid email is required.\"\n                      />\n                      <textarea\n                        id=\"comment_form_message\"\n                        className=\"text_field contact_form_message\"\n                        name=\"message\"\n                        placeholder=\"Message\"\n                        required=\"required\"\n                        data-error=\"Please, write us a message.\"\n                        defaultValue={\"\"}\n                      />\n                      <button\n                        id=\"comment_send_btn\"\n                        type=\"submit\"\n                        className=\"comment_send_btn trans_200\"\n                        value=\"Submit\"\n                      >\n                        send message\n                      </button>\n                    </form>\n                  </div>\n                </div>\n              </div>\n              {/* Sidebar Column */}\n              <div className=\"col-lg-4\">\n                <div className=\"sidebar\">\n                  {/* Archives */}\n                  <div className=\"sidebar_section\">\n                    <div className=\"sidebar_section_title\">\n                      <h3>Archives</h3>\n                    </div>\n                    <ul className=\"sidebar_list\">\n                      <li className=\"sidebar_list_item\">\n                        <a href=\"#\">Design Courses</a>\n                      </li>\n                      <li className=\"sidebar_list_item\">\n                        <a href=\"#\">All you need to know</a>\n                      </li>\n                      <li className=\"sidebar_list_item\">\n                        <a href=\"#\">Uncategorized</a>\n                      </li>\n                      <li className=\"sidebar_list_item\">\n                        <a href=\"#\">About Our Departments</a>\n                      </li>\n                      <li className=\"sidebar_list_item\">\n                        <a href=\"#\">Choose the right course</a>\n                      </li>\n                    </ul>\n                  </div>\n                  {/* Latest Posts */}\n                  <div className=\"sidebar_section\">\n                    <div className=\"sidebar_section_title\">\n                      <h3>Latest posts</h3>\n                    </div>\n                    <div className=\"latest_posts\">\n                      {/* Latest Post */}\n                      <div className=\"latest_post\">\n                        <div className=\"latest_post_image\">\n                          <img\n                            src=\"images/latest_1.jpg\"\n                            alt=\"https://unsplash.com/@dsmacinnes\"\n                          />\n                        </div>\n                        <div className=\"latest_post_title\">\n                          <a href=\"news_post.html\">\n                            Why do you need a qualification?\n                          </a>\n                        </div>\n                        <div className=\"latest_post_meta\">\n                          <span className=\"latest_post_author\">\n                            <a href=\"#\">By Christian Smith</a>\n                          </span>\n                          <span>|</span>\n                          <span className=\"latest_post_comments\">\n                            <a href=\"#\">3 Comments</a>\n                          </span>\n                        </div>\n                      </div>\n                      {/* Latest Post */}\n                      <div className=\"latest_post\">\n                        <div className=\"latest_post_image\">\n                          <img\n                            src=\"images/latest_2.jpg\"\n                            alt=\"https://unsplash.com/@erothermel\"\n                          />\n                        </div>\n                        <div className=\"latest_post_title\">\n                          <a href=\"news_post.html\">\n                            Why do you need a qualification?\n                          </a>\n                        </div>\n                        <div className=\"latest_post_meta\">\n                          <span className=\"latest_post_author\">\n                            <a href=\"#\">By Christian Smith</a>\n                          </span>\n                          <span>|</span>\n                          <span className=\"latest_post_comments\">\n                            <a href=\"#\">3 Comments</a>\n                          </span>\n                        </div>\n                      </div>\n                      {/* Latest Post */}\n                      <div className=\"latest_post\">\n                        <div className=\"latest_post_image\">\n                          <img\n                            src=\"images/latest_3.jpg\"\n                            alt=\"https://unsplash.com/@element5digital\"\n                          />\n                        </div>\n                        <div className=\"latest_post_title\">\n                          <a href=\"news_post.html\">\n                            Why do you need a qualification?\n                          </a>\n                        </div>\n                        <div className=\"latest_post_meta\">\n                          <span className=\"latest_post_author\">\n                            <a href=\"#\">By Christian Smith</a>\n                          </span>\n                          <span>|</span>\n                          <span className=\"latest_post_comments\">\n                            <a href=\"#\">3 Comments</a>\n                          </span>\n                        </div>\n                      </div>\n                    </div>\n                  </div>\n                  {/* Tags */}\n                  <div className=\"sidebar_section\">\n                    <div className=\"sidebar_section_title\">\n                      <h3>Tags</h3>\n                    </div>\n                    <div className=\"tags d-flex flex-row flex-wrap\">\n                      <div className=\"tag\">\n                        <a href=\"#\">Course</a>\n                      </div>\n                      <div className=\"tag\">\n                        <a href=\"#\">Design</a>\n                      </div>\n                      <div className=\"tag\">\n                        <a href=\"#\">FAQ</a>\n                      </div>\n                      <div className=\"tag\">\n                        <a href=\"#\">Teachers</a>\n                      </div>\n                      <div className=\"tag\">\n                        <a href=\"#\">School</a>\n                      </div>\n                      <div className=\"tag\">\n                        <a href=\"#\">Graduate</a>\n                      </div>\n                    </div>\n                  </div>\n                </div>\n              </div>\n            </div>\n          </div>\n        </div>\n\n        <Footer/>\n\n\n      </div>\n    );\n  }\n}"]},"sourceType":"script","hash":"ce8eda7dc9f30ad95eae56bcb0d1cbd01760b524"}
